debuggerPy/debugs.py
debuggerPy-0.0.2.dist-info/LICENSE
debuggerPy-0.0.2.dist-info/METADATA
debuggerPy-0.0.2.dist-info/WHEEL
debuggerPy-0.0.2.dist-info/top_level.txt
debuggerPy-0.0.2.dist-info/RECORD
