Metadata-Version: 2.1
Name: debuggerPy
Version: 0.0.2
Summary: Projeto criado com o intuito de facilitar o dabug de variaveis em python
Author-email: Wesley Marques <wesleymr59@gmail.com>
Project-URL: Homepage, https://github.com/wesleymr59/debug-variavel-py
Project-URL: Bug Tracker, https://github.com/wesleymr59/debug-variavel-py/issues
Classifier: Programming Language :: Python :: 3
Classifier: License :: OSI Approved :: MIT License
Classifier: Operating System :: OS Independent
Requires-Python: >=3.7
License-File: LICENSE
